bindglobal/__init__.py
bindglobal-0.0.3.dist-info/METADATA
bindglobal-0.0.3.dist-info/WHEEL
bindglobal-0.0.3.dist-info/top_level.txt
bindglobal-0.0.3.dist-info/RECORD
